Metadata-Version: 2.1
Name: odoo11-addon-l10n-ch-pain-credit-transfer
Version: 11.0.1.0.1
Summary: Generate ISO 20022 credit transfert (SEPA and not SEPA)
Home-page: https://github.com/OCA/l10n-switzerland
Author: Akretion,Camptocamp,Odoo Community Association (OCA)
Author-email: support@odoo-community.org
License: AGPL-3
Platform: UNKNOWN
Classifier: Programming Language :: Python
Classifier: Framework :: Odoo
Classifier: License :: OSI Approved :: GNU Affero General Public License v3
Requires-Python: >=2.7, !=3.0.*, !=3.1.*, !=3.2.*, !=3.3.*, !=3.4.*
Requires-Dist: odoo11-addon-account-banking-sepa-credit-transfer
Requires-Dist: odoo11-addon-l10n-ch-base-bank
Requires-Dist: odoo11-addon-l10n-ch-pain-base
Requires-Dist: odoo (<11.1dev,>=11.0a)
